{
  "positions": [
    {
      "id": "board",
      "position": {
        "x": 321.33333333333326,
        "y": 58.00000000000003
      },
      "compState": true,
      "flipped": false,
      "rotation": 0,
      "color": "black"
    },
    {
      "id": "button-1768846019543-0.9906203427978161",
      "position": {
        "x": 124.66666666666674,
        "y": 46.00000000000003
      },
      "compState": false,
      "flipped": false,
      "rotation": 0,
      "color": "gray"
    },
    {
      "id": "led-1768846069603-0.8785795903764011",
      "position": {
        "x": 160.66666666666663,
        "y": 169.33333333333331
      },
      "compState": true,
      "flipped": false,
      "rotation": 0,
      "color": "red"
    }
  ],
  "connections": [
    {
      "id": "button-1768846019543-0.9906203427978161-upright-GNDA",
      "x1": 548.208381652832,
      "y1": 122.5666732788086,
      "x2": 345.38336181640625,
      "y2": 86.28334045410156,
      "codoX": 349.29998779296875,
      "codoY": 136.5666732788086,
      "fromPinId": "GNDA",
      "toPinId": "button-1768846019543-0.9906203427978161-upright",
      "stroke": "black",
      "strokeWidth": 3
    },
    {
      "id": "button-1768846019543-0.9906203427978161-downleft-GPIO4",
      "x1": 548.208381652832,
      "y1": 180.1333236694336,
      "x2": 252.39996337890625,
      "y2": 116.28334045410156,
      "codoX": 252.29998779296875,
      "codoY": 194.1333236694336,
      "fromPinId": "GPIO4",
      "toPinId": "button-1768846019543-0.9906203427978161-downleft",
      "stroke": "black",
      "strokeWidth": 3
    },
    {
      "id": "led-1768846069603-0.8785795903764011-right-GPIO5",
      "x1": 548.208381652832,
      "y1": 194.5833282470703,
      "x2": 334.89996337890625,
      "y2": 319.2666931152344,
      "codoX": 410.4000244140625,
      "codoY": 251.6999969482422,
      "fromPinId": "GPIO5",
      "toPinId": "led-1768846069603-0.8785795903764011-right",
      "stroke": "black",
      "strokeWidth": 3
    },
    {
      "id": "led-1768846069603-0.8785795903764011-left-GNDC",
      "x1": 548.208381652832,
      "y1": 309.8666534423828,
      "x2": 319.89996337890625,
      "y2": 319.2666931152344,
      "codoX": 423.4000244140625,
      "codoY": 357.6999969482422,
      "fromPinId": "GNDC",
      "toPinId": "led-1768846069603-0.8785795903764011-left",
      "stroke": "black",
      "strokeWidth": 3
    }
  ],
  "boardData": {
    "name": "risv-esp32c3-devkitc-02",
    "author": "Elisa Utrilla Arroyo - UC3M",
    "pins": [
      "GNDA",
      "3v3A",
      "3v3B",
      "GPIO4",
      "GPIO5",
      "GPIO6",
      "GPIO7",
      "GNDB",
      "GPIO9",
      "5v5A",
      "5v5B",
      "GNDC",
      "GNDD",
      "GPIO0",
      "GPIO1",
      "GPIO2",
      "GPIO3",
      "GNDE",
      "GPIO10",
      "GNDF",
      "GPIO20",
      "GPIO21",
      "GNDG",
      "GPIO18",
      "GPIO19",
      "GNDH",
      "GNDI",
      "RST1",
      "GPIO8"
    ]
  },
  "code": "\n.data\n    time:  .word 1000\n    buttonPin: .word  4\n    ledpin: .word 5\n    buttonState:    .word   0\n    msg:    .string     \"Button Pressed!\"\n\n.text\nsetup:\n    li a0, 115200\n    addi sp, sp, -4      \n    sw ra, 0(sp)          \n    jal ra, serial_begin\n    lw ra, 0(sp)          \n    addi sp, sp, 4            \n\n    #pinMode(buttonPin,INPUT_PULLUP)\n    la a0, buttonPin   \n    lw a0, 0(a0)       \n    li a1,  0x05 #INPUT_PULLUP\n    addi sp, sp, -4      \n    sw ra, 0(sp)   \n    jal ra, pinMode\n    lw ra, 0(sp)          \n    addi sp, sp, 4\n    \n    #pinMode(ledpin,OUTPUT)\n    la a0, ledpin\n    lw a0, 0(a0)       \n    li a1,  0x03 #OUTPUT\n    addi sp, sp, -4      \n    sw ra, 0(sp)   \n    jal ra, pinMode\n    lw ra, 0(sp)          \n    addi sp, sp, 4\n\n    jr ra\n\nbutton_pressed:\n    la a0, msg\n    addi sp, sp, -16       \n    sw ra, 12(sp)          \n    jal ra, serial_printf\n    lw ra, 12(sp)          \n    addi sp, sp, 16       \n    \n    la a0, ledpin\n    lw a0, 0(a0)\n    li a1, 0x1\n    jal ra, digitalWrite\n    \n    la a0, time\n    lw a0, 0(a0)\n    addi sp, sp, -16      \n    sw ra, 12(sp)\n    jal ra, delay\n    lw ra, 12(sp)          \n    addi sp, sp, 16 \n    \n    jal ra, loop\n\n\nloop:\n    la a0, buttonPin   \n    lw a0, 0(a0)       \n    addi sp, sp, -4      \n    sw ra, 0(sp)          \n    jal ra, digitalRead\n    lw ra, 0(sp)          \n    addi sp, sp, 4\n\n    mv t0,a0\n\n    li t1 ,0 #LOW\n\n    beq t0,t1,button_pressed\n    \n    la a0, ledpin\n    lw a0, 0(a0)\n    li a1, 0x0\n    jal ra, digitalWrite\n    \n    la a0, time\n    lw a0, 0(a0)\n    addi sp, sp, -16      \n    sw ra, 12(sp)\n    jal ra, delay\n    lw ra, 12(sp)          \n    addi sp, sp, 16 \n\n    j loop\n\nmain:\n    addi sp, sp, -16       \n    sw ra, 12(sp)          \n    jal ra, initArduino    \n    jal ra, setup\n    lw ra, 12(sp)          \n    addi sp, sp, 16 \n    j loop\n    jr ra\n"
}